{
	"bounds": {
		"h": 1077.0,
		"w": 1920.0,
		"x": 0.0,
		"y": 0.0
	},
	"mapId": "area1/m1",
	"solids": [
		{
			"kind": "poly",
			"verts": [
				{
					"x": 177.0,
					"y": 223.375
				},
				{
					"x": 355.5,
					"y": 223.375
				},
				{
					"x": 355.5,
					"y": 238.875
				},
				{
					"x": 177.0,
					"y": 238.875
				}
			]
		},
		{
			"kind": "poly",
			"verts": [
				{
					"x": 270.299987792969,
					"y": 727.662536621094
				},
				{
					"x": 395.25,
					"y": 727.662536621094
				},
				{
					"x": 395.25,
					"y": 738.512512207031
				},
				{
					"x": 270.299987792969,
					"y": 738.512512207031
				}
			]
		},
		{
			"kind": "poly",
			"verts": [
				{
					"x": 1403.10009765625,
					"y": 321.137481689453
				},
				{
					"x": 1563.75,
					"y": 321.137481689453
				},
				{
					"x": 1563.75,
					"y": 335.087493896484
				},
				{
					"x": 1403.10009765625,
					"y": 335.087493896484
				}
			]
		},
		{
			"kind": "poly",
			"verts": [
				{
					"x": 1288.69995117188,
					"y": 751.087524414063
				},
				{
					"x": 1520.75,
					"y": 751.087524414063
				},
				{
					"x": 1520.75,
					"y": 771.237548828125
				},
				{
					"x": 1288.69995117188,
					"y": 771.237548828125
				}
			]
		}
	],
	"version": 1757027716
}